mergexp/__init__.py
mergexp/addr.py
mergexp/constraint.py
mergexp/elements.py
mergexp/enums.py
mergexp/exceptions.py
mergexp/unit.py
mergexp/pb/__init__.py
mergexp/pb/core_pb2.py
mergexp/pb/core_pb2_grpc.py
mergexp-0.3.0.dist-info/METADATA
mergexp-0.3.0.dist-info/WHEEL
mergexp-0.3.0.dist-info/top_level.txt
mergexp-0.3.0.dist-info/RECORD
